korean_word_relay/__init__.py
korean_word_relay/utils.py
korean_word_relay/word_relay.py
korean_word_relay/data/korean5800.txt
korean_word_relay-0.0.6.dist-info/METADATA
korean_word_relay-0.0.6.dist-info/WHEEL
korean_word_relay-0.0.6.dist-info/top_level.txt
korean_word_relay-0.0.6.dist-info/RECORD
