Metadata-Version: 2.1
Name: korean-word-relay
Version: 0.0.6
Summary: 끝말잇기 package for python
Home-page: https://github.com/5yearsKim/korean_word_relay
Author: 5yearsKim
Author-email: hypothesis22@gmail.com
License: UNKNOWN
Platform: UNKNOWN
Requires-Dist: hgtk
